pwptemp/__init__.py
pwptemp/heat_coefficients.py
pwptemp/inputs.py
pwptemp/linearsystem.py
pwptemp/main.py
pwptemp/plot.py
pwptemp/well_system.py
pwptemp-0.3.6.dist-info/LICENSE.md
pwptemp-0.3.6.dist-info/METADATA
pwptemp-0.3.6.dist-info/WHEEL
pwptemp-0.3.6.dist-info/top_level.txt
pwptemp-0.3.6.dist-info/RECORD
