Metadata-Version: 2.1
Name: pwptemp
Version: 0.3.6
Summary: Well Temperature Distribution
Home-page: https://github.com/pro-well-plan/pwptemp
Author: Pro Well Plan AS
Author-email: juan@prowellplan.com
License: LGPL v3
Keywords: well temperature distribution
Platform: UNKNOWN
Classifier: Programming Language :: Python :: 3
Classifier: License :: OSI Approved :: GNU Lesser General Public License v3 (LGPLv3)
Classifier: Natural Language :: English
Classifier: Topic :: Scientific/Engineering
Classifier: Topic :: Software Development
Classifier: Topic :: Software Development :: Libraries
Classifier: Topic :: Utilities
Requires-Dist: numpy
Requires-Dist: plotly
Requires-Dist: torque-drag
Requires-Dist: scipy
Requires-Dist: well-profile
